{
  "appPageId" : "329e0341-d0b0-4b81-8df0-864ef1fbc28e",
  "componentName" : "siteforce:sldsOneColLayout",
  "dataProviders" : [ ],
  "id" : "d5e2fccc-cf4a-4445-afcc-936320ae2565",
  "label" : "Record Detail",
  "regions" : [ {
    "id" : "32d1de7e-79c2-4995-a428-8049b9b25f9e",
    "regionName" : "header",
    "type" : "region"
  }, {
    "components" : [ {
      "componentAttributes" : {
        "recordId" : "{!recordId}"
      },
      "componentName" : "forceCommunity:recordHeadline",
      "id" : "b466e1c8-af18-473b-a0b9-bf8ae5bec072",
      "renderPriority" : "NEUTRAL",
      "renditionMap" : { },
      "type" : "component"
    }, {
      "componentAttributes" : {
        "detailsTabLabel" : "Details",
        "discussionsTabLabel" : "Feed",
        "recordId" : "{!recordId}",
        "relatedTabLabel" : "Related",
        "tab1Type" : "details",
        "tab2Type" : "related",
        "tab3Type" : "chatter",
        "tab4Type" : "none",
        "timelineTabLabel" : "Activity"
      },
      "componentName" : "forceCommunity:recordHomeTabs",
      "id" : "f3b9936e-0443-444f-9fbb-1ef4fb7918be",
      "renderPriority" : "NEUTRAL",
      "renditionMap" : { },
      "type" : "component"
    } ],
    "id" : "5aed3d8e-e308-4b41-8bb5-6de50cbe0408",
    "regionName" : "content",
    "type" : "region"
  }, {
    "id" : "952630a8-7e8d-4e1c-bd64-279c17898020",
    "regionName" : "footer",
    "type" : "region"
  }, {
    "components" : [ {
      "componentAttributes" : {
        "customHeadTags" : "",
        "description" : "",
        "title" : "{!Record._Object}: {!Record._Title}"
      },
      "componentName" : "forceCommunity:seoAssistant",
      "id" : "16e993e6-22af-489a-8202-860154fd435a",
      "renditionMap" : { },
      "type" : "component"
    } ],
    "id" : "286656ee-72be-4f18-8dfb-80e6c856039f",
    "regionName" : "sfdcHiddenRegion",
    "type" : "region"
  } ],
  "themeLayoutType" : "Inner",
  "type" : "view",
  "viewType" : "detail"
}